{
  "name": "Carrie Wilkins",
  "age": 39,
  "address": {
    "street": "Fumet Grove",
    "city": "Avjivzec",
    "state": "MD",
    "zip": "17351"
  },
  "contact": {
    "phone": "(655) 568-5589",
    "servicePhone": "800854996"
  },
  "birthday": "1983-05-06T16:41:01.882Z",
  "ip": "212.167.106.232",
  "foo": "bar",
  "profile": {
    "about": "Gapama ibopni ewoidji ja tietize uka puhegik emaetsim duvibuja mimrafuv utiw zahte bun tabebib tor cubiwopa rikik avuka. Wegibed kud oroim pazvivse bergiral wuf ha hu mih da ulwi gadejuazu. Goama dosje rer ibokavhaf kuvoccod lowzad tecorep jur wele ob taldatru wit imavi il jarofi ho onaza haegu. Coclabej zez rulveede radlapoz agki zun sav pazozsed nul bu divof opijogpaw uweeki guhuzok fi zulat libelis. Zu legatopu riet hibvohip li do refa bogupja jaz obaeb mubsoga emizafhe ked pe fega zejafuhec joh re.",
    "bio": "Uhe vilnic cankaflad nuffij iviolo oti fiowe feg pegovgi kulzez tecot pewlo douho. Soke mujaglob mosbelle ecadawa bit haafa ro tanodif riz zorkeh kacji mos. Ep dafjil wo avnauko jabu mon najiz vorkow bacocun cofdamkur ar ufaele. Semec sezabuk erlutnir numatuk oveklow we oh odigelec rojkace hekduwzeg cobbi tabubepe bijhejcu zut befib faluec be."
  },
  "apiKey": "2df6d40ca85f84ff66865db0a850f708416ebf62517a62518ce1e380b4637adb",
  "currency": {
    "code": "BRL",
    "name": "Brazil Real"
  }
}