{
  "name": "Christopher Hayes",
  "age": 20,
  "address": {
    "street": "Icuwa Place",
    "city": "Alnonel",
    "state": "OK",
    "zip": "14250"
  },
  "contact": {
    "phone": "(377) 415-6064",
    "servicePhone": "800676911"
  },
  "birthday": "1980-03-18T12:52:25.688Z",
  "ip": "191.252.149.16",
  "foo": "bar",
  "profile": {
    "about": "Fokjawba nuvezupu fohwa eh tijda kikoj dozvoso mudjerze taera pohto zahava juwij tilkon olvon seglo. Wovvutuh efirujoz jow urhoj kojafnuw do dururevup ide dunaj kiiru mebijni bittoftag lalji ripwaja hi wo me. Mat um kupi fef zenwadza ziwja ped moateam liimu jotwu cuuco opboskig pupasi to wuplivta. Rimludgon kiwkagoki fima caomo awsoc noj lo uguucefe nuviw nafuzpu zupwuzgi ifa gor sac davenal do.",
    "bio": "Miziktit ehazi te okifa higvabbi parwi ba umunofu je vadboku ibhug ceawako wihuf kitav raf iro jut. Ocafu togu vuvpul ec sanvi bav fakti fa otakus mapinek eno helewsib patowefa. Zu zufhibra cevok ona mipniti nec bijommuh lidfudon gecele eguwunhe cutwetso bumbe lofni zo. Taj to raruk cecupvo opwec sig hoffo olu oscijlub azejewepo beb funo wezokar botwog dewob diwipo. Lecte su cafug ivi az cuj lasubu wev ubnuse hi gowe ucojul ebefimap nikatuk guci. De vahuh we ipecuvpas worzuvi kuimtib kenut vot efi fuhup ehu siza op. Buod geh gopzefot kovlapab pozdeib ko ses sutbi kocu vosup lon pa taptibiho zoceeri fuufu kef."
  },
  "apiKey": "34801d5ff9239c6968acf4f35bfa0dafa15fa3cea62306af664605e2b45462c8",
  "currency": {
    "code": "SCR",
    "name": "Seychelles Rupee"
  }
}